pvview/__init__.py
pvview/_requirements.py
pvview/_version.py
pvview/pvview.py
pvview-1.0.0.dist-info/LICENSE
pvview-1.0.0.dist-info/METADATA
pvview-1.0.0.dist-info/WHEEL
pvview-1.0.0.dist-info/entry_points.txt
pvview-1.0.0.dist-info/top_level.txt
pvview-1.0.0.dist-info/RECORD
