Metadata-Version: 2.1
Name: pvview
Version: 1.0.0
Summary: display one or more EPICS PVs in a PyDM GUI window as a table
Home-page: https://github.com/BCDA-APS/pvview/
Author: Pete R. Jemian
Author-email: jemian@anl.gov
License: OPEN SOURCE LICENSE
Download-URL: https://github.com/BCDA-APS/pvview/
Keywords: Python,Qt5,PyDM,EPICS
Platform: any
Classifier: Development Status :: 4 - Beta
Classifier: Environment :: Console
Classifier: Environment :: Web Environment
Classifier: Intended Audience :: Science/Research
Classifier: License :: Free To Use But Restricted
Classifier: Operating System :: OS Independent
Classifier: Programming Language :: Python
Classifier: Topic :: Software Development :: Libraries :: Python Modules
Classifier: Topic :: Utilities
Requires-Dist: PyDM
